ytgrid/__init__.py
ytgrid/cli.py
ytgrid/automation/__init__.py
ytgrid/automation/browser.py
ytgrid/automation/player.py
ytgrid/backend/__init__.py
ytgrid/backend/main.py
ytgrid/backend/routes.py
ytgrid/backend/session_store.py
ytgrid/backend/task_manager.py
ytgrid/utils/__init__.py
ytgrid/utils/config.py
ytgrid/utils/logger.py
ytgrid-1.0.1.dist-info/METADATA
ytgrid-1.0.1.dist-info/WHEEL
ytgrid-1.0.1.dist-info/entry_points.txt
ytgrid-1.0.1.dist-info/top_level.txt
ytgrid-1.0.1.dist-info/RECORD
