Metadata-Version: 2.2
Name: ytgrid
Version: 1.0.1
Summary: YTGrid is a powerful, scalable, and flexible YT automation tool that enables looped playback, remote control, and real-time tracking using a hybrid CLI + API architecture. It integrates FastAPI for REST API control, Selenium for browser automation, and Python multiprocessing for concurrent tasks.
Home-page: https://github.com/sandy-sp/ytgrid
Author: Sandeep Paidipati
Author-email: sandeep.paidipati@gmail.com
Classifier: Programming Language :: Python :: 3
Classifier: License :: OSI Approved :: MIT License
Classifier: Operating System :: OS Independent
Requires-Python: >=3.8
Requires-Dist: fastapi
Requires-Dist: uvicorn
Requires-Dist: selenium
Requires-Dist: webdriver-manager
Requires-Dist: requests
Requires-Dist: rich
Requires-Dist: python-dotenv
Requires-Dist: websocket-client
Requires-Dist: bs4
Dynamic: author
Dynamic: author-email
Dynamic: classifier
Dynamic: description
Dynamic: description-content-type
Dynamic: home-page
Dynamic: requires-dist
Dynamic: requires-python
Dynamic: summary
